Workbook
Name _Toc301930468: TestDesign!#REF!
Name _Toc301930478: TestDesign!#REF!
Name ACTION: #REF!
Name LOCAL_DATE_SEPARATOR: #REF!
Name LOCAL_DAY_FORMAT: #REF!
Name LOCAL_HOUR_FORMAT: #REF!
Name LOCAL_MINUTE_FORMAT: #REF!
Name LOCAL_MONTH_FORMAT: #REF!
Name LOCAL_SECOND_FORMAT: #REF!
Name LOCAL_TIME_SEPARATOR: #REF!
Name LOCAL_YEAR_FORMAT: #REF!

Sheet Cover
B2: TEST CASE
B4: Project Name | C4: AB-SD | F4: Creator | G4: Nguyễn Văn A
B5: Project Code | C5: AB-SD | F5: Reviewer/Approver | G5: Trần Thị B
B6: Document Code | C6: =C5&"_TestCase_V0.1" -> AB-SD_TestCase_V0.1 | F6: Issue Date | G6: 42019
F7: Version | G7: 0.1
B10: Record of change
B11: Effective Date | C11: Version | D11: Change Item | E11: *A,D,M | F11: Change description | G11: Reference
B12: 42019 | C12: 0.1 | E12: A | F12: Create sample file of Test Case | G12: AB-SD_Software Requirements Specification

Sheet Test case List
D1: TEST CASE LIST
B3: Project Name | D3: =Cover!C4 -> AB-SD
B4: Project Code | D4: =Cover!C5 -> AB-SD
B5: Test Environment Setup Description | D5: <List enviroment requires in this system 1. Server 2. Database 3. Web Browser ... >
B8: No | C8: Function Name | D8: Sheet Name | E8: Description | F8: Pre-Condition
B9: 1 | C9: List Organisation | D9: List Organisation'!A1
B10: 2 | C10: Add Organisation | D10: Add Organisation'!A1
C11: <Add more function names here>

Sheet TestDesign
A1: Requirement Level 1 | B1: Requirement Level 2 | C1: Requirement Level 3 | D1: Test Criteria | E1: Test Type | F1: Note
A2: Confirm Order Product | B2: Product Displaying | C2: Display Product Information | D2: Ensure that the product image, name, color, and price are correctly displayed. | E2: Function | F2: Verify that all product details are clearly visible and accurate.
D3: Verify that the product image and description match the details of the selected product. | E3: Function
D4: Ensure that the product is available and displays correctly upon page load | E4: Function
B5: Customer Information | C5: Enter Customer Information | D5: Check that all customer information fields (Full Name, Phone Number, Email) can be correctly filled and validated. | E5: Function
D6: Ensure that mandatory fields cannot be left blank | E6: Function
D7: Validate the email format follows standard email conventions (e.g., user@example.com). | E7: Function
D8: Check that phone number is 10 number and start by 0. | E8: Function
D9: Check that an alert is displayed if the name exceeds 50 characters. | E9: Function
B10: Delivery Options | C10: Home Delivery | D10: Check if users can select a delivery address and time slot. | E10: Function | F10: Option to choose an alternative recipient is available.
D11: Ensure users can add a new delivery address and save it to their account | E11: Function
D12: Verify that users can select a shipping address from the saved list | E12: Function
C13: Store Pickup | D13: Check if users can select a store location and request technical support if needed. | E13: Function | F13: Store must be from an available list.
D14: Ensure delivery date and time options are available in real-time. | E14: Function
D15: Verify that users can select the nearest store for pickup and display store hours. | E15: Function
B16: Discount Codes and Loyalty Points | C16: Apply Discount Code | D16: The code must be valid and not expired. | E16: Function | F16: Immediate feedback if the code is invalid or expired.
D17: Display an error message if the discount code is invalid or expired | E17: Function
C18: Use Loyalty Points | D18: The customer must be logged in, and the points used should not exceed their balance. | E18: Function | F18: Points are converted into a discount.
D19: Confirm that the system does not allow both loyalty points and a discount code to be used simultaneously if restricted. | E19: Function
B20: Electronic Invoice Request | C20: Company Invoice | D20: Enter valid company name, tax identification number, and address. | E20: Function | F20: Mandatory if selecting Company type.
C21: Personal Invoice | D21: Enter a valid address and email for receiving the invoice | E21: Function | F21: Address and email must be correctly formatted.
B22: Payment Methods | C22: Credit/Debit Card Payment | D22: Ensure valid card information with card number, expiration date, and CVV. | E22: Function | F22: Supports Visa, MasterCard, and Amex.
C23: Digital Wallet | D23: Log in to the wallet account and verify. | E23: Function | F23: Supports MoMo, ZaloPay, Apple Pay.
C24: Bank Transfer | D24: Follow bank transfer instructions and confirm. | E24: Function
C25: Cash on Delivery | D25: Check eligible areas for this payment method | E25: Function
B26: Confirm and Place Order | C26: Order Confirmation | D26: Ensure information is correct before clicking “Place Order.” | E26: Function | F26: Requires user agreement to the terms of service.
D27: Confirm that users receive a confirmation message upon successful order placement. | E27: Function
D28: Ensure users must agree to the terms and conditions before placing the order | E28: Function
D29: Check that the "Place Order" button functions and redirects to the confirmation screen. | E29: Function

Sheet Login-Logout
A2: Module Code | B2: ListOrganisation | J2: Passed
A3: Test requirement | B3: List Organisation | J3: Failed
A4: Tester | B4: Nguyen Van A | J4: Blocked
A5: Passed | B5: Failed | C5: Untested | D5: Blocked | E5: Skipped | F5: Number of Test cases | J5: Untested
A6: =COUNTIF(F9:F996,"Passed") -> 7 | B6: =COUNTIF(F9:F996,"Failed") -> 2 | C6: =F6-E6-D6-B6-A6 -> 0 | D6: =COUNTIF(F$9:F$996,"Blocked") -> 0 | E6: =COUNTIF(F$9:F$996,"Skipped") -> 0 | F6: =COUNTA(A9:A996) -> 9 | J6: Skipped
A8: ID | B8: Test Case Description | C8: Test Case Procedure | D8: Expected Output | E8: Inter-test case Dependence | F8: Result | G8: Test date | H8: Note
A9: =IF(OR(B9<>"",D9<>""),"["&TEXT($B$2,"##")&"-"&TEXT(ROW()-8,"##")&"]","") -> [ListOrganisation-1] | B9: Test Login form | E9: Log in with role = Administrator (Permission = 3) | F9: Passed | G9: 42019
A10: =IF(OR(B10<>"",D10<>""),"["&TEXT($B$2,"##")&"-"&TEXT(ROW()-8,"##")&"]","") -> [ListOrganisation-2] | B10: Check filter organisation by letter "A" | C10: Pre-condition: + In DB, there're: - 50 active Organisations with 20 organisations that name is started by character "a" or "A" - 10 in-active Organisations with 5 organisations that name is started by character "a" or "A" Step: 1. On home page, select [Organisations] menu 2. On Organisation List screen, click on link "A" 3. Tick [Include In-active] checkbox | D10: 1. All 50 prepared active Organisations are displayed in 4 pages of Organisation List screen. 2. Only 20 prepared organisations that name is started by character "a" or "A", are displayed in 2 pages of Organisation List screen. 3. 25 prepared organisations (both active & in-active) that name is started by character "a" or "A", are displayed in 2 pages of Organisation List screen. | E10: Log in with role = Administrator (Permission = 3) | F10: Passed | G10: 42019
A11: =IF(OR(B11<>"",D11<>""),"["&TEXT($B$2,"##")&"-"&TEXT(ROW()-8,"##")&"]","") -> [ListOrganisation-3] | B11: Check sorting organisation list by Postcode | C11: 1. On home page, click on header column [Postcode] 2. Click on header column [Postcode] one more time | D11: 1. Still 25 prepared organisations (both active & in-active) that name is started by character "a" or "A", are displayed in 2 pages and sorted by Postcode (ascending). 2. Still 25 prepared organisations (both active & in-active) that name is started by character "a" or "A", are displayed in 2 pages and sorted by Postcode (descending). | E11: Org_List_02 | F11: Passed | G11: 42019
A12: =IF(OR(B12<>"",D12<>""),"["&TEXT($B$2,"##")&"-"&TEXT(ROW()-8,"##")&"]","") -> [ListOrganisation-4] | B12: Check filter "All" and sorting organisation list by name | C12: 1. On Organisation List screen, click on link "All" 2. On home page, click on header column [Organisation Name] 3. Click on header column [Organisation Name] one more time | D12: 1. All 70 prepared Organisations (both active & in-active) are displayed in 5 pages and sorted by Postcode (descending). 2. All 70 prepared Organisations are sorted by name (ascending) 3. All 70 prepared Organisations are sorted by name (descending) | E12: Org_List_03 | F12: Passed | G12: 42019
A13: =IF(OR(B13<>"",D13<>""),"["&TEXT($B$2,"##")&"-"&TEXT(ROW()-8,"##")&"]","") -> [ListOrganisation-5] | B13: Check paging next Organisation List screen | C13: 1. On Organisation List screen, click on Next page link 2. Input [3] into page number textbox 3. Click on Last page link | D13: 1. Page 2 with 15 next organisations is displayed and still sorted by name (descending). 2. Page 3 with 15 next organisations is displayed and still sorted by name (descending). 3. Page 5 with 10 last organisations is displayed and still sorted by name (descending). | E13: Org_List_04 | F13: Passed | G13: 42019
A14: =IF(OR(B14<>"",D14<>""),"["&TEXT($B$2,"##")&"-"&TEXT(ROW()-8,"##")&"]","") -> [ListOrganisation-6] | B14: Check paging previous Organisation List screen | C14: 1. On Organisation List screen, input [4] into page number textbox 2. Click on Previous page link 3. Click on First page link | D14: 1. Page 4 with 15 previous organisations is displayed and still sorted by name (descending). 2. Page 3 with 15 previous organisations is displayed and still sorted by name (descending). 3. Page 1 with 15 first organisations is displayed and still sorted by name (descending). | E14: Org_List_05 | F14: Passed | G14: 42019
A15: =IF(OR(B15<>"",D15<>""),"["&TEXT($B$2,"##")&"-"&TEXT(ROW()-8,"##")&"]","") -> [ListOrganisation-7] | B15: Check view Organisation Detail screen of active organisation | C15: 1. On Organisation List screen, select an active organisation by clicking on name of the organisation 2. Organisation Detail screen, click [Back] button | D15: 1. Organisation Detail screen of the selected organisation is displayed 2. Back to Organisation List screen as before step 1 | F15: Passed | G15: 42019
A16: =IF(OR(B16<>"",D16<>""),"["&TEXT($B$2,"##")&"-"&TEXT(ROW()-8,"##")&"]","") -> [ListOrganisation-8] | B16: Check view Organisation Detail screen of in-active organisation | C16: 1. On Organisation List screen, select an in-active organisation by clicking on name of the organisation 2. Click [Cancel] button on message 3. Repeat step 1 again 4. Click [OK] button on message | D16: 1. Message “Do you want to make this Organization active?” (with 2 buttons: [OK] and [Cancel]) is displayed. 2. Message is closed and back to Organisation List screen as before step 1. 3. Message “Do you want to make this Organization active?” (with 2 buttons: [OK] and [Cancel]) is displayed. 4. Message is closed and Organisation Detail screen of the selected organisation is displayed | F16: Failed | G16: 42019 | H16: <DefectID-1>
A17: =IF(OR(B17<>"",D17<>""),"["&TEXT($B$2,"##")&"-"&TEXT(ROW()-8,"##")&"]","") -> [ListOrganisation-9] | B17: Check the in-active organisation is changed to active after displaying detail screen | C17: 1. On Organisation Detail screen, click [Back] button | D17: 1. Back to Organisation List screen as before step 3 of case Org_List_08 | E17: Org_List_08 | F17: Failed | G17: 42019 | H17: <DefectID-2>

Sheet List Organisation
A2: Module Code | B2: ListOrganisation | J2: Passed
A3: Test requirement | B3: List Organisation | J3: Failed
A4: Tester | B4: Nguyen Van A | J4: Blocked
A5: Passed | B5: Failed | C5: Untested | D5: Blocked | E5: Skipped | F5: Number of Test cases | J5: Untested
A6: =COUNTIF(F9:F996,"Passed") -> 7 | B6: =COUNTIF(F9:F996,"Failed") -> 2 | C6: =F6-E6-D6-B6-A6 -> 0 | D6: =COUNTIF(F$9:F$996,"Blocked") -> 0 | E6: =COUNTIF(F$9:F$996,"Skipped") -> 0 | F6: =COUNTA(A9:A996) -> 9 | J6: Skipped
A8: ID | B8: Test Case Description | C8: Test Case Procedure | D8: Expected Output | E8: Inter-test case Dependence | F8: Result | G8: Test date | H8: Note
A9: =IF(OR(B9<>"",D9<>""),"["&TEXT($B$2,"##")&"-"&TEXT(ROW()-8,"##")&"]","") -> [ListOrganisation-1] | B9: Check displaying Organisation List screen by clicking on [Organisations] from the menu | C9: Pre-condition: + In DB, there're 50 active Organisations & 10 in-active Organisations Step: 1. On home page, select [Organisations] menu 2. On Organisation List screen, tick [Include In-active] checkbox | D9: 1. Organisation List screen is displayed. + 50 prepared active Organisations are displayed in 4 pages + Each 15 Organisations / page + All Organisations are sorted follow Organisation Name 2. All organisations are displayed on Organisation List screen. + 70 prepared Organisations (both active & in-active) are displayed in 5 pages + Each 15 Organisations / page + All Organisations are sorted follow Organisation Name | E9: Log in with role = Administrator (Permission = 3) | F9: Passed | G9: 42019
A10: =IF(OR(B10<>"",D10<>""),"["&TEXT($B$2,"##")&"-"&TEXT(ROW()-8,"##")&"]","") -> [ListOrganisation-2] | B10: Check filter organisation by letter "A" | C10: Pre-condition: + In DB, there're: - 50 active Organisations with 20 organisations that name is started by character "a" or "A" - 10 in-active Organisations with 5 organisations that name is started by character "a" or "A" Step: 1. On home page, select [Organisations] menu 2. On Organisation List screen, click on link "A" 3. Tick [Include In-active] checkbox | D10: 1. All 50 prepared active Organisations are displayed in 4 pages of Organisation List screen. 2. Only 20 prepared organisations that name is started by character "a" or "A", are displayed in 2 pages of Organisation List screen. 3. 25 prepared organisations (both active & in-active) that name is started by character "a" or "A", are displayed in 2 pages of Organisation List screen. | E10: Log in with role = Administrator (Permission = 3) | F10: Passed | G10: 42019
A11: =IF(OR(B11<>"",D11<>""),"["&TEXT($B$2,"##")&"-"&TEXT(ROW()-8,"##")&"]","") -> [ListOrganisation-3] | B11: Check sorting organisation list by Postcode | C11: 1. On home page, click on header column [Postcode] 2. Click on header column [Postcode] one more time | D11: 1. Still 25 prepared organisations (both active & in-active) that name is started by character "a" or "A", are displayed in 2 pages and sorted by Postcode (ascending). 2. Still 25 prepared organisations (both active & in-active) that name is started by character "a" or "A", are displayed in 2 pages and sorted by Postcode (descending). | E11: Org_List_02 | F11: Passed | G11: 42019
A12: =IF(OR(B12<>"",D12<>""),"["&TEXT($B$2,"##")&"-"&TEXT(ROW()-8,"##")&"]","") -> [ListOrganisation-4] | B12: Check filter "All" and sorting organisation list by name | C12: 1. On Organisation List screen, click on link "All" 2. On home page, click on header column [Organisation Name] 3. Click on header column [Organisation Name] one more time | D12: 1. All 70 prepared Organisations (both active & in-active) are displayed in 5 pages and sorted by Postcode (descending). 2. All 70 prepared Organisations are sorted by name (ascending) 3. All 70 prepared Organisations are sorted by name (descending) | E12: Org_List_03 | F12: Passed | G12: 42019
A13: =IF(OR(B13<>"",D13<>""),"["&TEXT($B$2,"##")&"-"&TEXT(ROW()-8,"##")&"]","") -> [ListOrganisation-5] | B13: Check paging next Organisation List screen | C13: 1. On Organisation List screen, click on Next page link 2. Input [3] into page number textbox 3. Click on Last page link | D13: 1. Page 2 with 15 next organisations is displayed and still sorted by name (descending). 2. Page 3 with 15 next organisations is displayed and still sorted by name (descending). 3. Page 5 with 10 last organisations is displayed and still sorted by name (descending). | E13: Org_List_04 | F13: Passed | G13: 42019
A14: =IF(OR(B14<>"",D14<>""),"["&TEXT($B$2,"##")&"-"&TEXT(ROW()-8,"##")&"]","") -> [ListOrganisation-6] | B14: Check paging previous Organisation List screen | C14: 1. On Organisation List screen, input [4] into page number textbox 2. Click on Previous page link 3. Click on First page link | D14: 1. Page 4 with 15 previous organisations is displayed and still sorted by name (descending). 2. Page 3 with 15 previous organisations is displayed and still sorted by name (descending). 3. Page 1 with 15 first organisations is displayed and still sorted by name (descending). | E14: Org_List_05 | F14: Passed | G14: 42019
A15: =IF(OR(B15<>"",D15<>""),"["&TEXT($B$2,"##")&"-"&TEXT(ROW()-8,"##")&"]","") -> [ListOrganisation-7] | B15: Check view Organisation Detail screen of active organisation | C15: 1. On Organisation List screen, select an active organisation by clicking on name of the organisation 2. Organisation Detail screen, click [Back] button | D15: 1. Organisation Detail screen of the selected organisation is displayed 2. Back to Organisation List screen as before step 1 | F15: Passed | G15: 42019
A16: =IF(OR(B16<>"",D16<>""),"["&TEXT($B$2,"##")&"-"&TEXT(ROW()-8,"##")&"]","") -> [ListOrganisation-8] | B16: Check view Organisation Detail screen of in-active organisation | C16: 1. On Organisation List screen, select an in-active organisation by clicking on name of the organisation 2. Click [Cancel] button on message 3. Repeat step 1 again 4. Click [OK] button on message | D16: 1. Message “Do you want to make this Organization active?” (with 2 buttons: [OK] and [Cancel]) is displayed. 2. Message is closed and back to Organisation List screen as before step 1. 3. Message “Do you want to make this Organization active?” (with 2 buttons: [OK] and [Cancel]) is displayed. 4. Message is closed and Organisation Detail screen of the selected organisation is displayed | F16: Failed | G16: 42019 | H16: <DefectID-1>
A17: =IF(OR(B17<>"",D17<>""),"["&TEXT($B$2,"##")&"-"&TEXT(ROW()-8,"##")&"]","") -> [ListOrganisation-9] | B17: Check the in-active organisation is changed to active after displaying detail screen | C17: 1. On Organisation Detail screen, click [Back] button | D17: 1. Back to Organisation List screen as before step 3 of case Org_List_08 | E17: Org_List_08 | F17: Failed | G17: 42019 | H17: <DefectID-2>

Sheet Add Organisation
A2: Module Code | B2: AddOrganisation | J2: Passed
A3: Test requirement | B3: Add Organisation | J3: Failed
A4: Tester | B4: Nguyen Van A | J4: Blocked
A5: Passed | B5: Failed | C5: Untested | D5: Blocked | E5: Skipped | F5: Number of Test cases | J5: Untested
A6: =COUNTIF(F9:F996,"Passed") -> 3 | B6: =COUNTIF(F9:F996,"Failed") -> 2 | C6: =F6-E6-D6-B6-A6 -> 1 | D6: =COUNTIF(F$9:F$996,"Blocked") -> 0 | E6: =COUNTIF(F$9:F$996,"Skipped") -> 0 | F6: =COUNTA(A9:A996) -> 6 | J6: Skipped
A8: ID | B8: Test Case Description | C8: Test Case Procedure | D8: Expected Output | E8: Inter-test case Dependence | F8: Result | G8: Test date | H8: Note
A9: =IF(OR(B9<>"",D9<>""),"["&TEXT($B$2,"##")&"-"&TEXT(ROW()-8,"##")&"]","") -> [AddOrganisation-1] | B9: Check adding new organisation with only mandatory field | C9: 1. On Organisation List screen, click [Create] button 2. On Organisation Detail screen, input value for mandatory fields - Organisation Name - Organisation Short Description - Type of Business - Address Line 1 - Postcode - Phone Number 3. Click [Save] button 4. Click [Back] button | D9: 1. The Organisation Detail screen with all blank fields is displayed. 3. The Organisation Detail screen is still displayed - 3 tabs [Detail 4], [Detail 5] & [BU/Directorates] are displayed - Message "Save Organisation successfully." is displayed 4. Back to Organisation List screen - New organisation is displayed in list - Organisation list is still sorted as before adding | F9: Passed | G9: 42019
A10: =IF(OR(B10<>"",D10<>""),"["&TEXT($B$2,"##")&"-"&TEXT(ROW()-8,"##")&"]","") -> [AddOrganisation-2] | B10: Check mandatory field | C10: 1. On Organisation List screen, click [Create] button 2. On Organisation Detail screen, input value for mandatory fields except: - Phone Number 3. Click [Save] button 4. Click [Back] button * Mandatory fields - Organisation Name - Organisation Short Description - Type of Business - Address Line 1 - Postcode - Phone Number | D10: 3. The Organisation Detail screen is still displayed - Message "Please input the phone number" is displayed 4. Back to Organisation List screen - No new organisation is added into organisation list - Organisation list is still sorted as before adding | F10: Failed | G10: 42019 | H10: <DefectID 3>
A11: =IF(OR(B11<>"",D11<>""),"["&TEXT($B$2,"##")&"-"&TEXT(ROW()-8,"##")&"]","") -> [AddOrganisation-3] | B11: Check can continue to add new organisation after error message | C11: 1. On Organisation List screen, click [Create] button 2. On Organisation Detail screen, input value for mandatory fields except: - Postcode 3. Click [Save] button 4. Input value for Postcode field 5. Click [Save] button 6. Click [Back] button * Mandatory fields - Organisation Name - Organisation Short Description - Type of Business - Address Line 1 - Postcode - Phone Number | D11: 3. The Organisation Detail screen is still displayed. - Message "Please input the postcode" is displayed. 5. The Organisation Detail screen is still displayed. - 3 tabs [Detail 4], [Detail 5] & [BU/Directorates] are displayed - Message "Save Organisation successfully." is displayed. 6. Back to Organisation List screen - New organisation is displayed in list. | F11: Passed | G11: 42019
A12: =IF(OR(B12<>"",D12<>""),"["&TEXT($B$2,"##")&"-"&TEXT(ROW()-8,"##")&"]","") -> [AddOrganisation-4] | B12: Check unique field - Organisation Name | C12: Pre-condition: + There's an organisation with Organisation Name = <name> (Example: [TestABC]) Step: 1. On Organisation List screen, click [Create] button 2. On Organisation Detail screen, input value for all mandatory fields - Organisation Name = [TestABC] 3. Click [Save] button | D12: 3. The Organisation Detail screen is still displayed. - Message "This "TestABC" name existed in system" is displayed. | F12: Failed | G12: 42019 | H12: <DefectID 4>
A13: =IF(OR(B13<>"",D13<>""),"["&TEXT($B$2,"##")&"-"&TEXT(ROW()-8,"##")&"]","") -> [AddOrganisation-5] | B13: Check can add some organisations continuously | C13: 1. On Organisation List screen, click [Create] button 2. On Organisation Detail screen, input value for all fields 3. Click [Save] button 4. Click [Save] button one more time 5. Change Organisation name 6. Click [Save] button one more time 7. Click [Back] button | D13: 3. The Organisation Detail screen is still displayed. - 3 tabs [Detail 4], [Detail 5] & [BU/Directorates] are displayed. - Message "Save Organisation successfully." is displayed. 4. Message "This "<organisation name>" name existed in system" is displayed. 6. The Organisation Detail screen is still displayed. - 3 tabs [Detail 4], [Detail 5] & [BU/Directorates] are displayed. - Message "Save Organisation successfully." is displayed. 7. Back to Organisation List screen - 2 new organisations are displayed in list. | F13: Passed | G13: 42019
A14: =IF(OR(B14<>"",D14<>""),"["&TEXT($B$2,"##")&"-"&TEXT(ROW()-8,"##")&"]","") -> [AddOrganisation-6] | B14: Check cancelling add organisation | C14: 1. On Organisation List screen, click [Create] button 2. On Organisation Detail screen, input value for all fields 3. Click [Back] button | D14: 3. Back to Organisation List screen. - No new organisation is displayed in list. | F14: Untested

Sheet Amend Organisation
A2: Module Code | B2: AmendOrganisation | J2: Passed
A3: Test requirement | B3: Amend Organisation | J3: Failed
A4: Tester | B4: Nguyen Van A | J4: Blocked
A5: Passed | B5: Failed | C5: Untested | D5: Blocked | E5: Skipped | F5: Number of Test cases | J5: Untested
A6: =COUNTIF(F9:F996,"Passed") -> 0 | B6: =COUNTIF(F9:F996,"Failed") -> 0 | C6: =F6-E6-D6-B6-A6 -> 4 | D6: =COUNTIF(F$9:F$996,"Blocked") -> 1 | E6: =COUNTIF(F$9:F$996,"Skipped") -> 1 | F6: =COUNTA(A9:A996) -> 6 | J6: Skipped
A8: ID | B8: Test Case Description | C8: Test Case Procedure | D8: Expected Output | E8: Inter-test case Dependence | F8: Result | G8: Test date | H8: Note
A9: =IF(OR(B9<>"",D9<>""),"["&TEXT($B$2,"##")&"-"&TEXT(ROW()-8,"##")&"]","") -> [AmendOrganisation-1] | B9: Check editing an active organisation | C9: 1. On Organisation List screen, select an active organisation by clicking on name of the organisation 2. Organisation Detail screen, change value of some fields 3. Click [Save] button 4. Click [Back] button | D9: 1. Organisation Detail screen of the selected organisation is displayed 3. Message "Save Organisation successfully." is displayed 4. Back to Organisation List screen - No new organisation is displayed in list - The selected organisation is updated as change in step 2 - Organisation list is still sorted as before adding | F9: Blocked | G9: 42019 | H9: <Reason or defect Id which makes this TC blocked>
A10: =IF(OR(B10<>"",D10<>""),"["&TEXT($B$2,"##")&"-"&TEXT(ROW()-8,"##")&"]","") -> [AmendOrganisation-2] | B10: Check editing an in-active organisation | C10: 1. On Organisation List screen, select an in-active organisation by clicking on name of the organisation 2. Click [OK] button on message 3. Organisation Detail screen, change value of some fields 4. Click [Save] button 5. Click [Back] button | D10: 1. Message “Do you want to make this Organization active?” (with 2 buttons: [OK] and [Cancel]) is displayed. 2. Message is closed and Organisation Detail screen of the selected organisation is displayed 4. Message "Save Organisation successfully." is displayed 5. Back to Organisation List screen - No new organisation is displayed in list - The selected organisation is updated as change in step 3 - Organisation list is still sorted as before adding | F10: Skipped | H10: <Reason or defect Id which makes this TC skipped>
A11: =IF(OR(B11<>"",D11<>""),"["&TEXT($B$2,"##")&"-"&TEXT(ROW()-8,"##")&"]","") -> [AmendOrganisation-3] | B11: Check cancelling edit an active organisation | C11: 1. On Organisation List screen, select an active organisation by clicking on name of the organisation 2. Organisation Detail screen, change value of some fields 3. Click [Back] button | D11: 1. Organisation Detail screen of the selected organisation is displayed 3. Back to Organisation List screen - No new organisation is displayed in list - The selected organisation is NOT changed any | F11: Untested
A12: =IF(OR(B12<>"",D12<>""),"["&TEXT($B$2,"##")&"-"&TEXT(ROW()-8,"##")&"]","") -> [AmendOrganisation-4] | B12: Check mark In-active Organisation that doesn't link to a Service or a Premise | C12: 1. On Organisation List screen, select an active organisation that doesn't link to a Service or a Premise by clicking on name of the organisation 2. Organisation Detail screen, click [In-active] button | D12: 2. Back to Organisation List screen - The selected organisation is changed to in-active | F12: Untested
A13: =IF(OR(B13<>"",D13<>""),"["&TEXT($B$2,"##")&"-"&TEXT(ROW()-8,"##")&"]","") -> [AmendOrganisation-5] | B13: Check mark In-active Organisation that already link to a Service | C13: 1. On Organisation List screen, select an active organisation that already link to a Service by clicking on name of the organisation 2. Organisation Detail screen, click [In-active] button 3. Click [OK] button on message | D13: 2. Message "This Organization is already in use, do you want to make this in-active?” (with 2 button [OK] & [Cancel]) is displayed 3. Back to Organisation List screen - The selected organisation is changed to in-active | F13: Untested
A14: =IF(OR(B14<>"",D14<>""),"["&TEXT($B$2,"##")&"-"&TEXT(ROW()-8,"##")&"]","") -> [AmendOrganisation-6] | B14: Check cancelling mark In-active Organisation that already link to a Service | C14: 1. On Organisation List screen, select an active organisation that already link to a Service by clicking on name of the organisation 2. Organisation Detail screen, click [In-active] button 3. Click [Cancel] button on message 4. Click [Back] button | D14: 2. Message "This Organization is already in use, do you want to make this in-active?” (with 2 button [OK] & [Cancel]) is displayed 3. Back to Organisation Detail screen 4. Back to Organisation List screen - The selected organisation is still in active (Not changed to in-active) | F14: Untested

Sheet Test Report
B1: TEST REPORT
B3: Project Name | C3: =Cover!C4 -> AB-SD | E3: Creator | G3: Nguyễn Văn A
B4: Project Code | C4: =Cover!C5 -> AB-SD | E4: Reviewer/Approver | G4: Trần Thị B
B5: Document Code | C5: =C4&"_"&"Test Report"&"_"&"v0.1" -> AB-SD_Test Report_v0.1 | E5: Issue Date | G5: 42019 | H5: <Date when this test report is created>
B6: Notes | C6: <List modules included in this release> ex: Release 1 includes 2 modules: Module1 and Module2
B10: No | C10: Module code | D10: Pass | E10: Fail | F10: Untested | G10: Blocked | H10: Skipped | I10: Number of test cases
B11: 1 | C11: ='List Organisation'!B2 -> ListOrganisation | D11: ='List Organisation'!A6 -> 7 | E11: ='List Organisation'!B6 -> 2 | F11: ='List Organisation'!C6 -> 0 | G11: ='List Organisation'!D6 -> 0 | H11: ='List Organisation'!E6 -> 0 | I11: ='List Organisation'!F6 -> 9
B12: 2 | C12: ='Add Organisation'!B2 -> AddOrganisation | D12: ='Add Organisation'!A6 -> 3 | E12: ='Add Organisation'!B6 -> 2 | F12: ='Add Organisation'!C6 -> 1 | G12: ='Add Organisation'!D6 -> 0 | H12: ='Add Organisation'!E6 -> 0 | I12: ='Add Organisation'!F6 -> 6
B13: 3 | C13: ='Amend Organisation'!B2 -> AmendOrganisation | D13: ='Amend Organisation'!A6 -> 0 | E13: ='Amend Organisation'!B6 -> 0 | F13: ='Amend Organisation'!C6 -> 4 | G13: ='Amend Organisation'!D6 -> 1 | H13: ='Amend Organisation'!E6 -> 1 | I13: ='Amend Organisation'!F6 -> 6
C15: Sub total | D15: =SUM(D9:D14) -> 10 | E15: =SUM(E9:E14) -> 4 | F15: =SUM(F9:F14) -> 5 | G15: =SUM(G9:G14) -> 1 | H15: =SUM(H9:H14) -> 1 | I15: =SUM(I9:I14) -> 21
C17: Test coverage | E17: =(D15+E15)*100/(I15-H15-G15) -> 73.684211 | F17: %
C18: Test successful coverage | E18: =D15*100/(D15+E15) -> 71.428571 | F18: %
